cbms/__init__.py
cbms/cbms.py
cbms-1.2.0.dist-info/DESCRIPTION.rst
cbms-1.2.0.dist-info/METADATA
cbms-1.2.0.dist-info/RECORD
cbms-1.2.0.dist-info/WHEEL
cbms-1.2.0.dist-info/metadata.json
cbms-1.2.0.dist-info/top_level.txt
