Metadata-Version: 2.0
Name: cbms
Version: 1.2.0
Summary: CBMS Studio API
Home-page: http://www.cbmsstudio.com
Author: Chris Gurtler
Author-email: gurtlerc@gmail.com
License: MIT
Keywords: bacnet raspberry development
Platform: UNKNOWN
Classifier: Development Status :: 4 - Beta
Classifier: Intended Audience :: Developers
Classifier: Topic :: Software Development :: Build Tools
Classifier: License :: OSI Approved :: MIT License
Classifier: Programming Language :: Python :: 2
Classifier: Programming Language :: Python :: 2.6
Classifier: Programming Language :: Python :: 2.7
Classifier: Programming Language :: Python :: 3
Classifier: Programming Language :: Python :: 3.3
Classifier: Programming Language :: Python :: 3.4
Classifier: Programming Language :: Python :: 3.5
Requires-Dist: cbms
